mlbot.py
mlbot_cloud-1.0.0.dist-info/METADATA
mlbot_cloud-1.0.0.dist-info/WHEEL
mlbot_cloud-1.0.0.dist-info/entry_points.txt
mlbot_cloud-1.0.0.dist-info/top_level.txt
mlbot_cloud-1.0.0.dist-info/RECORD
