Metadata-Version: 2.1
Name: mlbot-cloud
Version: 1.0.0
Summary: A fast & easy way to train ML models in your cloud, directly from your laptop.
Home-page: https://github.com/thecooltechguy/mlbot
Author: Subhash Ramesh
Author-email: suramesh@ucsd.edu
License: MIT
Platform: UNKNOWN
Classifier: License :: OSI Approved :: MIT License
Classifier: Programming Language :: Python :: 3
Requires-Dist: boto3 (==1.21.18)
Requires-Dist: click (==8.0.4)
Requires-Dist: PyYAML (==6.0)
Requires-Dist: requests (==2.27.1)
Requires-Dist: requests-oauthlib (==1.3.1)
Requires-Dist: yaspin (==2.1.0)
